### 2.10 String 相关的+

String中+常用于字符串的连接。

> ex:

``` java
/**
 *	String相关的+
 */
public void ex(){
    String a = "aa";
    String b = "bb";
    String c= "xx"+"yy"+a+"zz"+"mm"+b;
    System.out.println(c);
}
```

``` java
public static main([Ljava/lang/String;)V
   L0
    LINENUMBER 5 L0
    LDC "aa"
    ASTORE 1
   L1
    LINENUMBER 6 L1
    LDC "bb"
    ASTORE 2
   L2
    LINENUMBER 7 L2
    NEW java/lang/StringBuilder
    DUP
    LDC "xxyy "
    INVOKESPECIAL java/lang/StringBuilder.<init> (Ljava/lang/String;)V
    ALOAD 1
    INVOKEVIRTUAL java/lang/StringBuilder.append (Ljava/lang/String;)Ljava/lang/StringBuilder;
    LDC "zz"
    INVOKEVIRTUAL java/lang/StringBuilder.append (Ljava/lang/String;)Ljava/lang/StringBuilder;
    LDC "mm"
    INVOKEVIRTUAL java/lang/StringBuilder.append (Ljava/lang/String;)Ljava/lang/StringBuilder;
    ALOAD 2
    INVOKEVIRTUAL java/lang/StringBuilder.append (Ljava/lang/String;)Ljava/lang/StringBuilder;
    INVOKEVIRTUAL java/lang/StringBuilder.toString ()Ljava/lang/String;
    ASTORE 3
   L3
    LINENUMBER 8 L3
    GETSTATIC java/lang/System.out : Ljava/io/PrintStream;
    ALOAD 3
    INVOKEVIRTUAL java/io/PrintStream.println (Ljava/lang/String;)V
   L4
    LINENUMBER 9 L4
    RETURN
   L5
    LOCALVARIABLE args [Ljava/lang/String; L0 L5 0
    LOCALVARIABLE a Ljava/lang/String; L1 L5 1
    LOCALVARIABLE b Ljava/lang/String; L2 L5 2
    LOCALVARIABLE c Ljava/lang/String; L3 L5 3
    MAXSTACK = 3
    MAXLOCALS = 4
}
```

通过字节码可以得出如下几点结论：

1. String中使用 + 字符串连接符进行字符串连接时，连接操作最开始如果都是字符串常量，编译后将尽可能多的直接将字符串连接起来，形成新的字符串常量参与后续连接（通过反编译工具jd-gui也可以方便的直接看出）；

2. 接下来的字符串连接时从左到右依次进行，对于不同的字符串，首先以最左边的字符串为参数创建StringBuilder对象，然后依次对右边进行append操作，最后将StringBuilder对象通过toString()方法转换成String对象（注意：中间的多个字符串常量不会自动拼接）；

   **也就是说String c= "xx"+"yy"+"a"+"zz"+"mm"+"b";**

   实质上的实现过程是：

   **String c= new StringBuilder("xxyy").append(a).append("zz").append("mm").append(b).toString();**

   由此得出结论：当使用+进行多个字符串连接时，实际上时产生一个StringBuilder对象和一个String对象。