### 1.17 new String("abc")

使用这种方式一共创建两个字符串对象（前提试String Pool中还没有"abc"字符串对象）

* "abc"属于字符串字面量，因此编译时期会在String Pool中创建一个字符串对象，指向这个"abc"字符串字面量；
* 而使用new的方式会在堆中创建一个字符串对象。 

创建一个测试了，其中Main方法中使用这种方式来创建字符串对象。

``` java
public class Test(){
    public static void main(String[] args){
        String s = new String("abc");
    }
}
```

使用javap - verbose Test 进行反编译，得到以下内容：

``` java
Classfile /C:/Users/10134/Desktop/新建文件夹/Test.class
  Last modified 2020-4-8; size 332 bytes
  MD5 checksum c8c1a1562f5f07e5849494dbb05ea92a
  Compiled from "Test.java"
public class Test
  minor version: 0
  major version: 52
  flags: ACC_PUBLIC, ACC_SUPER
Constant pool:
   #1 = Methodref          #6.#15         // java/lang/Object."<init>":()V
   #2 = Class              #16            // java/lang/String
   #3 = String             #17            // abc
   #4 = Methodref          #2.#18         // java/lang/String."<init>":(Ljava/lang/String;)V
   #5 = Class              #19            // Test
   #6 = Class              #20            // java/lang/Object
   #7 = Utf8               <init>
   #8 = Utf8               ()V
   #9 = Utf8               Code
  #10 = Utf8               LineNumberTable
  #11 = Utf8               main
  #12 = Utf8               ([Ljava/lang/String;)V
  #13 = Utf8               SourceFile
  #14 = Utf8               Test.java
  #15 = NameAndType        #7:#8          // "<init>":()V
  #16 = Utf8               java/lang/String
  #17 = Utf8               abc
  #18 = NameAndType        #7:#21         // "<init>":(Ljava/lang/String;)V
  #19 = Utf8               Test
  #20 = Utf8               java/lang/Object
  #21 = Utf8               (Ljava/lang/String;)V
{
  public Test();
    descriptor: ()V
    flags: ACC_PUBLIC
    Code:
      stack=1, locals=1, args_size=1
         0: aload_0
         1: invokespecial #1                  // Method java/lang/Object."<init>":()V
         4: return
      LineNumberTable:
        line 1: 0

  public static void main(java.lang.String[]);
    descriptor: ([Ljava/lang/String;)V
    flags: ACC_PUBLIC, ACC_STATIC
    Code:
      stack=3, locals=2, args_size=1
         0: new           #2                  // class java/lang/String
         3: dup
         4: ldc           #3                  // String abc
         6: invokespecial #4                  // Method java/lang/String."<init>":(Ljava/lang/String;)V
         9: astore_1
        10: return
      LineNumberTable:
        line 3: 0
        line 4: 10
}
SourceFile: "Test.java"

```

在Constant Pool中，#17存储这个字符串字面量"abc"，#3是String Pool的字符串对象，它指向#17这个字符串字面量。在main方法中，0：行new #2在堆中创建一个字符串对象，并且使用 ldc #3将String Pool中的字符串对象作为String构造函数的参数。

以下是String构造函数的源码。可以看到，在将一个字符串对象作为另外一个字符串对象的构造函数参数时，并不会完全复制value数组内容，而是都会指向同一个value数组。

```  java
public String(String original) {
        this.value = original.value;
        this.hash = original.hash;
    }
```

